fancyhands/__init__.py
fancyhands_v3-3.0.1.dist-info/LICENCE.txt
fancyhands_v3-3.0.1.dist-info/METADATA
fancyhands_v3-3.0.1.dist-info/WHEEL
fancyhands_v3-3.0.1.dist-info/top_level.txt
fancyhands_v3-3.0.1.dist-info/RECORD
